setup.py
ele_mlcourse_distributions/Binomialdistribution.py
ele_mlcourse_distributions/Gaussiandistribution.py
ele_mlcourse_distributions/Generaldistribution.py
ele_mlcourse_distributions/__init__.py
ele_mlcourse_distributions.egg-info/PKG-INFO
ele_mlcourse_distributions.egg-info/SOURCES.txt
ele_mlcourse_distributions.egg-info/dependency_links.txt
ele_mlcourse_distributions.egg-info/not-zip-safe
ele_mlcourse_distributions.egg-info/top_level.txt