Metadata-Version: 1.0
Name: ele-mlcourse-distributions
Version: 0.1
Summary: Gaussian and Binomial distributions
Home-page: UNKNOWN
Author: Eleonora Mercalli
Author-email: eleonora.mercalli@gmail.com
License: UNKNOWN
Platform: UNKNOWN
